setup.py
grooveshark/__init__.py
grooveshark/client.py
grooveshark.egg-info/PKG-INFO
grooveshark.egg-info/SOURCES.txt
grooveshark.egg-info/dependency_links.txt
grooveshark.egg-info/not-zip-safe
grooveshark.egg-info/top_level.txt