Metadata-Version: 1.0
Name: grooveshark
Version: 0.01
Summary: Simple Grooveshark API Client
Home-page: http://github.com/girasquid/grooveshark/
Author: Luke Hutscal
Author-email: luke@creaturecreative.com
License: UNKNOWN
Platform: UNKNOWN
Classifier: Development Status :: 3 - Alpha
Classifier: Environment :: Web Environment
Classifier: Intended Audience :: Developers
Classifier: License :: OSI Approved :: MIT License
Classifier: Operating System :: OS Independent
Classifier: Programming Language :: Python
